saltx/__init__.py
saltx/bwvault.py
saltx/config.py
saltx/configtemplate.py
saltx/encfs.py
saltx/entry.py
saltx/exceptionlogger.py
saltx/gitrepo.py
saltx/logic.py
saltx/merge.py
saltx/processexec.py
saltx/queryuser.py
saltx/salt.py
saltx/setupenv.py
saltx/sshtools.py
saltx/userinteraction.py
saltx/vaultsync.py
saltx/yamlconfig.py
saltx-0.5.2.dist-info/LICENSE
saltx-0.5.2.dist-info/METADATA
saltx-0.5.2.dist-info/WHEEL
saltx-0.5.2.dist-info/entry_points.txt
saltx-0.5.2.dist-info/top_level.txt
saltx-0.5.2.dist-info/RECORD
