Metadata-Version: 2.2
Name: saltx
Version: 0.5.2
Summary: using Saltstack with Bitwarden/Vaultwarden credential management - locally or via salt-ssh
Home-page: https://www.github.com/towalink/saltx
Author: Dirk Henrici
Author-email: towalink.saltx@henrici.name
Project-URL: Project homepage, https://www.github.com/towalink/saltx
Project-URL: Repository, https://www.github.com/towalink/saltx
Project-URL: Documentation, https://www.github.com/towalink/saltx
Keywords: Saltstack Bitwarden Vaultwarden automation
Classifier: Programming Language :: Python
Classifier: Programming Language :: Python :: 3
Classifier: License :: OSI Approved :: GNU Affero General Public License v3 or later (AGPLv3+)
Classifier: Operating System :: POSIX :: Linux
Classifier: Development Status :: 4 - Beta
Classifier: Intended Audience :: System Administrators
Requires-Python: >=3.11
License-File: LICENSE
Requires-Dist: bwinterface
Requires-Dist: jinja2
Requires-Dist: pyyaml
Dynamic: author
Dynamic: author-email
Dynamic: classifier
Dynamic: description
Dynamic: description-content-type
Dynamic: home-page
Dynamic: keywords
Dynamic: project-url
Dynamic: requires-dist
Dynamic: requires-python
Dynamic: summary
